[
    {
      "front": "What is the national flower of Japan?",
      "back": "Cherry Blossom (Sakura)"
    },
    {
      "front": "Which flower is known as the 'queen of flowers'?",
      "back": "Rose"
    },
    {
      "front": "What flower symbolizes friendship?",
      "back": "Yellow Rose"
    },
    {
      "front": "Which flower is often associated with Valentine's Day?",
      "back": "Rose"
    },
    {
      "front": "Which flower is the symbol of purity in Christianity?",
      "back": "Lily"
    },
    {
      "front": "What flower is commonly used in making perfumes?",
      "back": "Jasmine"
    },
    {
      "front": "Which flower is known for its large, colorful blooms and attracts bees and butterflies?",
      "back": "Sunflower"
    },
    {
      "front": "Which flower is often used to symbolize peace?",
      "back": "Dove Orchid"
    },
    {
      "front": "What flower is known for its ability to bloom in the winter?",
      "back": "Snowdrop"
    },
    {
      "front": "Which flower is often used in traditional Hawaiian garlands?",
      "back": "Plumeria"
    }
  ]
  